setup.py
ts_arm/__init__.py
ts_arm/aug_rec.py
ts_arm/synth_trend_season.py
ts_arm/synthetic_F1_array.npy
ts_arm/utlis.py
ts_arm.egg-info/PKG-INFO
ts_arm.egg-info/SOURCES.txt
ts_arm.egg-info/dependency_links.txt
ts_arm.egg-info/requires.txt
ts_arm.egg-info/top_level.txt